README.rst
countminsketch.py
setup.py
countminsketch.egg-info/PKG-INFO
countminsketch.egg-info/SOURCES.txt
countminsketch.egg-info/dependency_links.txt
countminsketch.egg-info/top_level.txt